shapleyrouting/__init__.py
shapleyrouting/main.py
shapleyrouting/rideshare/__init__.py
shapleyrouting/rideshare/rideshare.py
shapleyrouting-0.1.0.dist-info/LICENSE.md
shapleyrouting-0.1.0.dist-info/WHEEL
shapleyrouting-0.1.0.dist-info/METADATA
shapleyrouting-0.1.0.dist-info/RECORD
