Metadata-Version: 2.1
Name: shapleyrouting
Version: 0.1.0
Summary: An implementation of efficient Shapley value calculation of routing problem
License: Apache-2.0
Author: Connor Sweet
Author-email: cssweet@uwaterloo.ca
Requires-Python: >=3.8, !=2.7.*, !=3.0.*, !=3.1.*, !=3.2.*, !=3.3.*, !=3.4.*, !=3.5.*, !=3.6.*, !=3.7.*
Classifier: License :: OSI Approved :: Apache Software License
Classifier: Programming Language :: Python :: 3
Classifier: Programming Language :: Python :: 3.9
Classifier: Programming Language :: Python :: 3.10
Classifier: Programming Language :: Python :: 3.11
Requires-Dist: geopy (>=2.3.0,<3.0.0)
Requires-Dist: numpy (>=1.24.2,<2.0.0)
Requires-Dist: streamlit (>=1.20.0,<2.0.0)
